source_fullstory/__init__.py
source_fullstory/manifest.yaml
source_fullstory/run.py
source_fullstory/schemas/blockrules.json
source_fullstory/schemas/domainsettings.json
source_fullstory/schemas/eventDefs.json
source_fullstory/schemas/geosettings.json
source_fullstory/schemas/operations.json
source_fullstory/schemas/recordingfeatures.json
source_fullstory/schemas/segments.json
source_fullstory/schemas/sessions.json
source_fullstory/schemas/targetrules.json
source_fullstory/schemas/webhooks.json
source_fullstory/source.py
source_fullstory/spec.yaml
airbyte_source_fullstory-0.1.14.dist-info/METADATA
airbyte_source_fullstory-0.1.14.dist-info/WHEEL
airbyte_source_fullstory-0.1.14.dist-info/entry_points.txt
airbyte_source_fullstory-0.1.14.dist-info/RECORD
